{
  "id": "clients/other-clients",
  "title": "Other MCP Clients",
  "description": "Rug Radar is a standard MCP server. Any client with remote MCP support can integrate it.",
  "source": "@site/docs/clients/other-clients.md",
  "sourceDirName": "clients",
  "slug": "/clients/other-clients",
  "permalink": "/docs/clients/other-clients",
  "draft": false,
  "unlisted": false,
  "tags": [],
  "version": "current",
  "frontMatter": {
    "id": "other-clients",
    "title": "Other MCP Clients"
  },
  "sidebar": "docsSidebar",
  "previous": {
    "title": "Using Rug Radar In Gemini",
    "permalink": "/docs/clients/gemini"
  },
  "next": {
    "title": "Data Sources Behind Results",
    "permalink": "/docs/data-sources"
  }
}